slimelearnpy/__init__.py
slimelearnpy/slimelearn.py
slimelearnpy-0.8.3.dist-info/LICENSE
slimelearnpy-0.8.3.dist-info/WHEEL
slimelearnpy-0.8.3.dist-info/METADATA
slimelearnpy-0.8.3.dist-info/RECORD
