Metadata-Version: 2.1
Name: slimelearnpy
Version: 0.8.3
Summary: slimelearn.py version
Home-page: https://github.com/javierburgosv/slimelearn.py
Author: Javier Burgos
Author-email: j.b.valdes@hotmail.com
Requires-Python: >= 3.9.1
Classifier: License :: OSI Approved :: MIT License
